[
  {
    "_host":"WORKSTATION5",
    "time_window":1604291700000,
    "total_events":184,
    "proc_create_count":2,
    "network_conn_count":0,
    "image_load_count":122,
    "proc_access_count":157,
    "file_create_count":11,
    "dns_query_count":0,
    "powershell_count":0,
    "encoded_cmd_count":0,
    "long_cmd_count":0,
    "office_spawn_count":0,
    "hack_tool_count":87,
    "attack_sig_count":0,
    "unsigned_count":2,
    "suspicious_dll_count":1,
    "lsass_access_count":2,
    "temp_write_count":0,
    "unique_processes":9,
    "unique_parents":2,
    "unique_users":3,
    "avg_cmd_len":0.3636363636,
    "max_cmd_len":57.0,
    "avg_proc_depth":1.512195122,
    "system_ctx_count":44,
    "anomaly_score":-0.5,
    "is_anomaly":false,
    "rule_score":94.0,
    "anomaly_risk":0.0,
    "severity_score":94.0,
    "severity":"High",
    "top_reasons":"LSASS Access, Hack Tool, Suspicious DLL, Unsigned Binary"
  }
]